{
  "dashboard_rrhh_costo_laboral_venta": 29.8,
  "dashboard_rrhh_rotacion": 11.5,
  "dashboard_rrhh_propinas": 4.2,
  "dashboard_rrhh_ausentismo": 4.1,
  "dashboard_rrhh_horas_extra": 285,
  "dashboard_rrhh_personal_activo": 112,
  "dashboard_rrhh_grafico_costo_laboral": {
    "grafico_meses": ["Jun", "Jul", "Ago", "Sep", "Oct", "Nov", "Dic"],
    "grafico_valores": [19, 22, 27.5, 23.5, 23, 30, 32.5],
    "grafico_meta": 25
  },
  "dashboard_rrhh_grafico_propinas": {
    "grafico_meses": ["Jun", "Jul", "Ago", "Sep", "Oct", "Nov", "Dic"],
    "grafico_valores": [3.2, 2.8, 4.5, 3.1, 3.8, 2.9, 5.2]
  },
  "dashboard_rrhh_grafico_rotacion": {
    "grafico_meses": ["Jun", "Jul", "Ago", "Sep", "Oct", "Nov", "Dic"],
    "grafico_valores": [10, 5, 7, 3, 7.5, 4, 12]
  },
  "dashboard_rrhh_grafico_ausentismo": {
    "grafico_meses": ["Jun", "Jul", "Ago", "Sep", "Oct", "Nov", "Dic"],
    "grafico_valores": [13, 6.5, 8.5, 4.5, 10, 6, 14]
  },
  "dashboard_rrhh_grafico_horas_extra": {
    "grafico_meses": ["Jun", "Jul", "Ago", "Sep", "Oct", "Nov", "Dic"],
    "grafico_valores": [285, 145, 195, 135, 210, 155, 325]
  }
}
