[
  {
    "trib_sucursal": "Sucursal Principal",
    "trib_tipo_impuesto": "IGV",
    "trib_base_imponible": 245680.00,
    "trib_tasa_porcentaje": 18,
    "trib_debito_fiscal": 44222.40,
    "trib_creditos_fiscales": 12500.00,
    "trib_impuesto_neto_pagar": 31722.40
  },
  {
    "trib_sucursal": "Sucursal Lima",
    "trib_tipo_impuesto": "Retenciones",
    "trib_base_imponible": 85000.00,
    "trib_tasa_porcentaje": 3,
    "trib_debito_fiscal": 2550.00,
    "trib_creditos_fiscales": 0.00,
    "trib_impuesto_neto_pagar": 2550.00
  },
  {
    "trib_sucursal": "Sucursal Arequipa",
    "trib_tipo_impuesto": "Percepciones",
    "trib_base_imponible": 45000.00,
    "trib_tasa_porcentaje": 2,
    "trib_debito_fiscal": 900.00,
    "trib_creditos_fiscales": 0.00,
    "trib_impuesto_neto_pagar": 900.00
  }
]
