[
  {
    "ubic_codigo": "EDI-001",
    "ubic_nombre": "Edificio Central",
    "ubic_nivel": "01",
    "ubic_descripcion": "Edificio principal de oficinas administrativas",
    "ubic_responsable": "Juan Pérez",
    "ubic_ubicacion_padre": "",
    "ubic_estado": "Activo",
    "ubic_cod_interno": "SIG-001",
    "ubic_observaciones": "",
    "ubic_org_hierarchy": ["EDI-001"]
  },
  {
    "ubic_codigo": "PIS-001",
    "ubic_nombre": "Piso 1",
    "ubic_nivel": "02",
    "ubic_descripcion": "Primer piso con áreas administrativas",
    "ubic_responsable": "María Garcia",
    "ubic_ubicacion_padre": "EDI-001",
    "ubic_estado": "Activo",
    "ubic_cod_interno": "SIG-002",
    "ubic_observaciones": "",
    "ubic_org_hierarchy": ["EDI-001", "PIS-001"]
  },
  {
    "ubic_codigo": "OFI-001",
    "ubic_nombre": "Oficina 101",
    "ubic_nivel": "03",
    "ubic_descripcion": "Oficina del gerente general",
    "ubic_responsable": "Carlos López",
    "ubic_ubicacion_padre": "PIS-001",
    "ubic_estado": "Activo",
    "ubic_cod_interno": "SIG-003",
    "ubic_observaciones": "",
    "ubic_org_hierarchy": ["EDI-001", "PIS-001", "OFI-001"]
  },
  {
    "ubic_codigo": "OFI-002",
    "ubic_nombre": "Oficina 102",
    "ubic_nivel": "03",
    "ubic_descripcion": "Departamento de recursos humanos",
    "ubic_responsable": "Ana Martínez",
    "ubic_ubicacion_padre": "PIS-001",
    "ubic_estado": "Activo",
    "ubic_cod_interno": "SIG-004",
    "ubic_observaciones": "",
    "ubic_org_hierarchy": ["EDI-001", "PIS-001", "OFI-002"]
  },
  {
    "ubic_codigo": "OFI-003",
    "ubic_nombre": "Oficina 103",
    "ubic_nivel": "03",
    "ubic_descripcion": "Oficina de ventas",
    "ubic_responsable": "Sofia Ramírez",
    "ubic_ubicacion_padre": "PIS-001",
    "ubic_estado": "Activo",
    "ubic_cod_interno": "SIG-005",
    "ubic_observaciones": "",
    "ubic_org_hierarchy": ["EDI-001", "PIS-001", "OFI-003"]
  },
  {
    "ubic_codigo": "OFI-004",
    "ubic_nombre": "Oficina 104",
    "ubic_nivel": "03",
    "ubic_descripcion": "Sala de juntas de reuniones",
    "ubic_responsable": "Carlos López",
    "ubic_ubicacion_padre": "PIS-001",
    "ubic_estado": "Activo",
    "ubic_cod_interno": "SIG-006",
    "ubic_observaciones": "",
    "ubic_org_hierarchy": ["EDI-001", "PIS-001", "OFI-004"]
  },
  {
    "ubic_codigo": "PIS-002",
    "ubic_nombre": "Piso 2 - Operaciones",
    "ubic_nivel": "02",
    "ubic_descripcion": "Segundo piso dedicado a operaciones",
    "ubic_responsable": "Pedro Sanchez",
    "ubic_ubicacion_padre": "EDI-001",
    "ubic_estado": "Activo",
    "ubic_cod_interno": "SIG-007",
    "ubic_observaciones": "",
    "ubic_org_hierarchy": ["EDI-001", "PIS-002"]
  },
  {
    "ubic_codigo": "OFI-005",
    "ubic_nombre": "Oficina de TI",
    "ubic_nivel": "03",
    "ubic_descripcion": "Departamento de tecnología",
    "ubic_responsable": "Miguel Torres",
    "ubic_ubicacion_padre": "PIS-002",
    "ubic_estado": "Activo",
    "ubic_cod_interno": "SIG-008",
    "ubic_observaciones": "",
    "ubic_org_hierarchy": ["EDI-001", "PIS-002", "OFI-005"]
  },
  {
    "ubic_codigo": "OFI-006",
    "ubic_nombre": "Centro de control",
    "ubic_nivel": "03",
    "ubic_descripcion": "Centro de monitoreo y control",
    "ubic_responsable": "Laura Mendoza",
    "ubic_ubicacion_padre": "PIS-002",
    "ubic_estado": "Activo",
    "ubic_cod_interno": "SIG-009",
    "ubic_observaciones": "",
    "ubic_org_hierarchy": ["EDI-001", "PIS-002", "OFI-006"]
  },
  {
    "ubic_codigo": "ALM-001",
    "ubic_nombre": "Almacén Principal",
    "ubic_nivel": "02",
    "ubic_descripcion": "Almacén de insumos y equipos",
    "ubic_responsable": "Luis Rodríguez",
    "ubic_ubicacion_padre": "EDI-001",
    "ubic_estado": "Activo",
    "ubic_cod_interno": "SIG-010",
    "ubic_observaciones": "",
    "ubic_org_hierarchy": ["EDI-001", "ALM-001"]
  },
  {
    "ubic_codigo": "PIS-005",
    "ubic_nombre": "Piso 5 - Capacitaciones",
    "ubic_nivel": "02",
    "ubic_descripcion": "Piso dedicado a capacitaciones",
    "ubic_responsable": "Gabriela Ortíz",
    "ubic_ubicacion_padre": "EDI-001",
    "ubic_estado": "Activo",
    "ubic_cod_interno": "SIG-011",
    "ubic_observaciones": "",
    "ubic_org_hierarchy": ["EDI-001", "PIS-005"]
  },
  {
    "ubic_codigo": "AUL-001",
    "ubic_nombre": "Aula de capacitación",
    "ubic_nivel": "03",
    "ubic_descripcion": "Aula para cursos y capacitaciones",
    "ubic_responsable": "Mónica Silva",
    "ubic_ubicacion_padre": "PIS-005",
    "ubic_estado": "Activo",
    "ubic_cod_interno": "SIG-012",
    "ubic_observaciones": "",
    "ubic_org_hierarchy": ["EDI-001", "PIS-005", "AUL-001"]
  },
  {
    "ubic_codigo": "AUL-002",
    "ubic_nombre": "Segunda aula de capacitaciones",
    "ubic_nivel": "03",
    "ubic_descripcion": "Aula para capacitaciones",
    "ubic_responsable": "Mónica Silva",
    "ubic_ubicacion_padre": "PIS-005",
    "ubic_estado": "Activo",
    "ubic_cod_interno": "SIG-013",
    "ubic_observaciones": "",
    "ubic_org_hierarchy": ["EDI-001", "PIS-005", "AUL-002"]
  },
  {
    "ubic_codigo": "EDI-002",
    "ubic_nombre": "Edificio Anexo",
    "ubic_nivel": "01",
    "ubic_descripcion": "Edificio anexo de almacenamiento",
    "ubic_responsable": "Roberto Díaz",
    "ubic_ubicacion_padre": "",
    "ubic_estado": "Activo",
    "ubic_cod_interno": "SIG-014",
    "ubic_observaciones": "",
    "ubic_org_hierarchy": ["EDI-002"]
  },
  {
    "ubic_codigo": "UB002-A1",
    "ubic_nombre": "Almacén Principal",
    "ubic_nivel": "02",
    "ubic_descripcion": "Almacén de productos terminados",
    "ubic_responsable": "Roberto Torres",
    "ubic_ubicacion_padre": "EDI-002",
    "ubic_estado": "Activo",
    "ubic_cod_interno": "SIG-015",
    "ubic_observaciones": "",
    "ubic_org_hierarchy": ["EDI-002", "UB002-A1"]
  },
  {
    "ubic_codigo": "UB002-A2",
    "ubic_nombre": "Almacén Secundario",
    "ubic_nivel": "02",
    "ubic_descripcion": "Almacén de materias primas",
    "ubic_responsable": "Sofia Ramirez",
    "ubic_ubicacion_padre": "EDI-002",
    "ubic_estado": "Inactivo",
    "ubic_cod_interno": "SIG-016",
    "ubic_observaciones": "",
    "ubic_org_hierarchy": ["EDI-002", "UB002-A2"]
  },
  {
    "ubic_codigo": "EDI-003",
    "ubic_nombre": "Planta de Producción",
    "ubic_nivel": "01",
    "ubic_descripcion": "Planta industrial de producción",
    "ubic_responsable": "Fernando Castro",
    "ubic_ubicacion_padre": "",
    "ubic_estado": "Activo",
    "ubic_cod_interno": "SIG-017",
    "ubic_observaciones": "",
    "ubic_org_hierarchy": ["EDI-003"]
  },
  {
    "ubic_codigo": "UB003-L1",
    "ubic_nombre": "Línea A",
    "ubic_nivel": "02",
    "ubic_descripcion": "Línea de ensamblaje A",
    "ubic_responsable": "Miguel Castro",
    "ubic_ubicacion_padre": "EDI-003",
    "ubic_estado": "Activo",
    "ubic_cod_interno": "SIG-018",
    "ubic_observaciones": "",
    "ubic_org_hierarchy": ["EDI-003", "UB003-L1"]
  },
  {
    "ubic_codigo": "UB003-L1-E1",
    "ubic_nombre": "Estación 1",
    "ubic_nivel": "03",
    "ubic_descripcion": "Estación de montaje inicial",
    "ubic_responsable": "Fernando Diaz",
    "ubic_ubicacion_padre": "UB003-L1",
    "ubic_estado": "Activo",
    "ubic_cod_interno": "SIG-019",
    "ubic_observaciones": "",
    "ubic_org_hierarchy": ["EDI-003", "UB003-L1", "UB003-L1-E1"]
  },
  {
    "ubic_codigo": "UB003-L1-E2",
    "ubic_nombre": "Estación 2",
    "ubic_nivel": "03",
    "ubic_descripcion": "Estación de ensamblaje final",
    "ubic_responsable": "Carmen Ruiz",
    "ubic_ubicacion_padre": "UB003-L1",
    "ubic_estado": "Activo",
    "ubic_cod_interno": "SIG-020",
    "ubic_observaciones": "",
    "ubic_org_hierarchy": ["EDI-003", "UB003-L1", "UB003-L1-E2"]
  }
]
