{
"ARTICULO_CATEG": [
	{
		"CAT_ART" : "021   ",
		"DESC_CATEGORIA" : "EQUIPOS DE REEMPLAZO",
		"FLAG_SERVICIO" : "0",
		"FLAG_ART_MANT" : "0",
		"COD_CLASE" : null,
		"GRUPO" : null,
		"FLAG_REPLICACION" : "1",
		"FLAG_ESTADO" : "1"
	},
	{
		"CAT_ART" : "003   ",
		"DESC_CATEGORIA" : "COMBUSTIBLES",
		"FLAG_SERVICIO" : "0",
		"FLAG_ART_MANT" : "0",
		"COD_CLASE" : null,
		"GRUPO" : null,
		"FLAG_REPLICACION" : "1",
		"FLAG_ESTADO" : "1"
	},
	{
		"CAT_ART" : "004   ",
		"DESC_CATEGORIA" : "EMBALAJES",
		"FLAG_SERVICIO" : "0",
		"FLAG_ART_MANT" : "0",
		"COD_CLASE" : null,
		"GRUPO" : null,
		"FLAG_REPLICACION" : "1",
		"FLAG_ESTADO" : "1"
	},
	{
		"CAT_ART" : "005   ",
		"DESC_CATEGORIA" : "ENVASES",
		"FLAG_SERVICIO" : "0",
		"FLAG_ART_MANT" : "0",
		"COD_CLASE" : null,
		"GRUPO" : null,
		"FLAG_REPLICACION" : "1",
		"FLAG_ESTADO" : "1"
	},
	{
		"CAT_ART" : "006   ",
		"DESC_CATEGORIA" : "FERRETERIA",
		"FLAG_SERVICIO" : "0",
		"FLAG_ART_MANT" : "0",
		"COD_CLASE" : null,
		"GRUPO" : null,
		"FLAG_REPLICACION" : "1",
		"FLAG_ESTADO" : "1"
	},
	{
		"CAT_ART" : "007   ",
		"DESC_CATEGORIA" : "IMPLEMENTOS DE SEGURIDAD Y PROTECCION",
		"FLAG_SERVICIO" : "0",
		"FLAG_ART_MANT" : "0",
		"COD_CLASE" : null,
		"GRUPO" : null,
		"FLAG_REPLICACION" : "1",
		"FLAG_ESTADO" : "1"
	},
	{
		"CAT_ART" : "008   ",
		"DESC_CATEGORIA" : "INSUMOS",
		"FLAG_SERVICIO" : "0",
		"FLAG_ART_MANT" : "0",
		"COD_CLASE" : null,
		"GRUPO" : null,
		"FLAG_REPLICACION" : "1",
		"FLAG_ESTADO" : "1"
	},
	{
		"CAT_ART" : "009   ",
		"DESC_CATEGORIA" : "LUBRICANTES",
		"FLAG_SERVICIO" : "0",
		"FLAG_ART_MANT" : "0",
		"COD_CLASE" : null,
		"GRUPO" : null,
		"FLAG_REPLICACION" : "1",
		"FLAG_ESTADO" : "1"
	},
	{
		"CAT_ART" : "010   ",
		"DESC_CATEGORIA" : "MATERIA PRIMA",
		"FLAG_SERVICIO" : "0",
		"FLAG_ART_MANT" : "0",
		"COD_CLASE" : null,
		"GRUPO" : null,
		"FLAG_REPLICACION" : "1",
		"FLAG_ESTADO" : "1"
	},
	{
		"CAT_ART" : "018   ",
		"DESC_CATEGORIA" : "ENVASES",
		"FLAG_SERVICIO" : "0",
		"FLAG_ART_MANT" : "0",
		"COD_CLASE" : null,
		"GRUPO" : null,
		"FLAG_REPLICACION" : "1",
		"FLAG_ESTADO" : "1"
	},
	{
		"CAT_ART" : "019   ",
		"DESC_CATEGORIA" : "MATERIALES AUXILIARES CONSERVAS DE PESCADO\n",
		"FLAG_SERVICIO" : "0",
		"FLAG_ART_MANT" : "0",
		"COD_CLASE" : null,
		"GRUPO" : null,
		"FLAG_REPLICACION" : "1",
		"FLAG_ESTADO" : "1"
	},
	{
		"CAT_ART" : "300   ",
		"DESC_CATEGORIA" : "SERVICIOS",
		"FLAG_SERVICIO" : "1",
		"FLAG_ART_MANT" : "0",
		"COD_CLASE" : null,
		"GRUPO" : null,
		"FLAG_REPLICACION" : "1",
		"FLAG_ESTADO" : "1"
	},
	{
		"CAT_ART" : "013   ",
		"DESC_CATEGORIA" : "REPUESTOS Y ACCESORIOS MAQUINARIAS Y EQUIPOS",
		"FLAG_SERVICIO" : "0",
		"FLAG_ART_MANT" : "0",
		"COD_CLASE" : null,
		"GRUPO" : null,
		"FLAG_REPLICACION" : "1",
		"FLAG_ESTADO" : "1"
	},
	{
		"CAT_ART" : "014   ",
		"DESC_CATEGORIA" : "SISTEMA DE FONDEO",
		"FLAG_SERVICIO" : "0",
		"FLAG_ART_MANT" : "0",
		"COD_CLASE" : null,
		"GRUPO" : null,
		"FLAG_REPLICACION" : "1",
		"FLAG_ESTADO" : "1"
	},
	{
		"CAT_ART" : "017   ",
		"DESC_CATEGORIA" : "ACTIVO FIJO",
		"FLAG_SERVICIO" : "0",
		"FLAG_ART_MANT" : "0",
		"COD_CLASE" : null,
		"GRUPO" : null,
		"FLAG_REPLICACION" : "1",
		"FLAG_ESTADO" : "1"
	},
	{
		"CAT_ART" : "011   ",
		"DESC_CATEGORIA" : "PRODUCTOS QUIMICOS",
		"FLAG_SERVICIO" : "0",
		"FLAG_ART_MANT" : "0",
		"COD_CLASE" : null,
		"GRUPO" : null,
		"FLAG_REPLICACION" : "1",
		"FLAG_ESTADO" : "1"
	},
	{
		"CAT_ART" : "012   ",
		"DESC_CATEGORIA" : "PRODUCTOS TERMINADOS",
		"FLAG_SERVICIO" : "0",
		"FLAG_ART_MANT" : "0",
		"COD_CLASE" : null,
		"GRUPO" : null,
		"FLAG_REPLICACION" : "1",
		"FLAG_ESTADO" : "1"
	},
	{
		"CAT_ART" : "001   ",
		"DESC_CATEGORIA" : "APAREJO DE PESCA",
		"FLAG_SERVICIO" : "0",
		"FLAG_ART_MANT" : "0",
		"COD_CLASE" : null,
		"GRUPO" : null,
		"FLAG_REPLICACION" : "1",
		"FLAG_ESTADO" : "1"
	},
	{
		"CAT_ART" : "002   ",
		"DESC_CATEGORIA" : "AVITUALLAMIENTO EN GENERAL",
		"FLAG_SERVICIO" : "0",
		"FLAG_ART_MANT" : "0",
		"COD_CLASE" : null,
		"GRUPO" : null,
		"FLAG_REPLICACION" : "1",
		"FLAG_ESTADO" : "1"
	},
	{
		"CAT_ART" : "015   ",
		"DESC_CATEGORIA" : "SISTEMA DE PROTECCION DEL CASCO",
		"FLAG_SERVICIO" : "0",
		"FLAG_ART_MANT" : "0",
		"COD_CLASE" : null,
		"GRUPO" : null,
		"FLAG_REPLICACION" : "1",
		"FLAG_ESTADO" : "1"
	},
	{
		"CAT_ART" : "016   ",
		"DESC_CATEGORIA" : "SUMINISTROS VARIOS",
		"FLAG_SERVICIO" : "0",
		"FLAG_ART_MANT" : "0",
		"COD_CLASE" : null,
		"GRUPO" : null,
		"FLAG_REPLICACION" : "1",
		"FLAG_ESTADO" : "1"
	},
	{
		"CAT_ART" : "020   ",
		"DESC_CATEGORIA" : "AREAS VERDES",
		"FLAG_SERVICIO" : "0",
		"FLAG_ART_MANT" : "0",
		"COD_CLASE" : null,
		"GRUPO" : null,
		"FLAG_REPLICACION" : "1",
		"FLAG_ESTADO" : "1"
	}
]}
