[
  {
    "reporte_planilla_numero_documento": "DNI - 70345882",
    "reporte_planilla_trabajador": "Jean Pierre Santíllán",
    "reporte_planilla_periodo": "202510",
    "reporte_planilla_contrato": "Indefinido",
    "reporte_planilla_sucursal": "La Molina, Lima",
    "reporte_planilla_centro_costo": "Administración",
    "reporte_planilla_salario_bruto": "S/ 3,500.00",
    "reporte_planilla_aumentos": "S/ 200.00",
    "reporte_planilla_descuentos_totales": "S/ 550.00",
    "reporte_planilla_neto_a_pagar": "S/ 2950.00",
    "reporte_planilla_adelantos": "S/ 400.00",
    "reporte_planilla_saldo_cta_cte": "-S/ 150.00",
    "reporte_planilla_ultima_modificacion": "06/11/2025",
    "reporte_planilla_estado": "Pendiente"
  },
  {
    "reporte_planilla_numero_documento": "DNI - 70345882",
    "reporte_planilla_trabajador": "Álvaro Ontaneda Herrazura",
    "reporte_planilla_periodo": "202510",
    "reporte_planilla_contrato": "Temporal",
    "reporte_planilla_sucursal": "Miraflores, Lima",
    "reporte_planilla_centro_costo": "Cocina",
    "reporte_planilla_salario_bruto": "S/ 3,500.00",
    "reporte_planilla_aumentos": "S/ 200.00",
    "reporte_planilla_descuentos_totales": "S/ 550.00",
    "reporte_planilla_neto_a_pagar": "S/ 2950.00",
    "reporte_planilla_adelantos": "S/ 400.00",
    "reporte_planilla_saldo_cta_cte": "S/ 150.00",
    "reporte_planilla_ultima_modificacion": "06/11/2025",
    "reporte_planilla_estado": "Pagado"
  },
  {
    "reporte_planilla_numero_documento": "EXT - 70345882",
    "reporte_planilla_trabajador": "Carlos Alberto Marquez Bron...",
    "reporte_planilla_periodo": "202510",
    "reporte_planilla_contrato": "Prácticas",
    "reporte_planilla_sucursal": "Miraflores, Lima",
    "reporte_planilla_centro_costo": "Almacén",
    "reporte_planilla_salario_bruto": "S/ 3,500.00",
    "reporte_planilla_aumentos": "S/ 200.00",
    "reporte_planilla_descuentos_totales": "S/ 550.00",
    "reporte_planilla_neto_a_pagar": "S/ 2950.00",
    "reporte_planilla_adelantos": "S/ 400.00",
    "reporte_planilla_saldo_cta_cte": "-S/ 150.00",
    "reporte_planilla_ultima_modificacion": "06/11/2025",
    "reporte_planilla_estado": "En revisión"
  },
  {
    "reporte_planilla_numero_documento": "DNI - 70345882",
    "reporte_planilla_trabajador": "Alexander Ellos Montearagaga...",
    "reporte_planilla_periodo": "202510",
    "reporte_planilla_contrato": "Indefinido",
    "reporte_planilla_sucursal": "Miraflores, Lima",
    "reporte_planilla_centro_costo": "Servicios Aseo",
    "reporte_planilla_salario_bruto": "S/ 3,500.00",
    "reporte_planilla_aumentos": "S/ 200.00",
    "reporte_planilla_descuentos_totales": "S/ 550.00",
    "reporte_planilla_neto_a_pagar": "S/ 2950.00",
    "reporte_planilla_adelantos": "S/ 400.00",
    "reporte_planilla_saldo_cta_cte": "-S/ 150.00",
    "reporte_planilla_ultima_modificacion": "06/11/2025",
    "reporte_planilla_estado": "En revisión"
  },
  {
    "reporte_planilla_numero_documento": "EXT - 70345882",
    "reporte_planilla_trabajador": "John Alberto Lemon Quispe",
    "reporte_planilla_periodo": "202510",
    "reporte_planilla_contrato": "Indefinido",
    "reporte_planilla_sucursal": "San Isidro, Lima",
    "reporte_planilla_centro_costo": "Cocina",
    "reporte_planilla_salario_bruto": "S/ 3,500.00",
    "reporte_planilla_aumentos": "S/ 200.00",
    "reporte_planilla_descuentos_totales": "S/ 550.00",
    "reporte_planilla_neto_a_pagar": "S/ 2950.00",
    "reporte_planilla_adelantos": "S/ 400.00",
    "reporte_planilla_saldo_cta_cte": "S/ 150.00",
    "reporte_planilla_ultima_modificacion": "06/11/2025",
    "reporte_planilla_estado": "En revisión"
  },
  {
    "reporte_planilla_numero_documento": "DNI - 70345882",
    "reporte_planilla_trabajador": "Paul Eusebio McCartney Solano",
    "reporte_planilla_periodo": "202510",
    "reporte_planilla_contrato": "Indefinido",
    "reporte_planilla_sucursal": "San Borja, Lima",
    "reporte_planilla_centro_costo": "Cocina",
    "reporte_planilla_salario_bruto": "S/ 3,500.00",
    "reporte_planilla_aumentos": "S/ 200.00",
    "reporte_planilla_descuentos_totales": "S/ 550.00",
    "reporte_planilla_neto_a_pagar": "S/ 2950.00",
    "reporte_planilla_adelantos": "S/ 400.00",
    "reporte_planilla_saldo_cta_cte": "S/ 150.00",
    "reporte_planilla_ultima_modificacion": "06/11/2025",
    "reporte_planilla_estado": "En revisión"
  }
]